duckdb_mcp_server/__init__.py
duckdb_mcp_server/config.py
duckdb_mcp_server/credentials.py
duckdb_mcp_server/database.py
duckdb_mcp_server/server.py
duckdb_mcp_server/resources/README.md
duckdb_mcp_server/resources/__init__.py
duckdb_mcp_server/resources/docs.py
duckdb_mcp_server/resources/xml/duckdb_data_import.xml
duckdb_mcp_server/resources/xml/duckdb_friendly_sql.xml
duckdb_mcp_server/resources/xml/duckdb_visualization.xml
duckdb_mcp_server-0.1.0.dist-info/METADATA
duckdb_mcp_server-0.1.0.dist-info/WHEEL
duckdb_mcp_server-0.1.0.dist-info/entry_points.txt
duckdb_mcp_server-0.1.0.dist-info/licenses/LICENSE
duckdb_mcp_server-0.1.0.dist-info/RECORD
