Metadata-Version: 2.4
Name: duckdb-mcp-server
Version: 0.1.0
Summary: A MCP server for DuckDB that enables LLMs to query and analyze data from various sources
Project-URL: Homepage, https://github.com/yourusername/duckdb-mcp-server
Project-URL: Bug Tracker, https://github.com/yourusername/duckdb-mcp-server/issues
License: MIT License
License-File: LICENSE
Classifier: License :: OSI Approved :: MIT License
Classifier: Operating System :: OS Independent
Classifier: Programming Language :: Python :: 3
Classifier: Programming Language :: Python :: 3.10
Classifier: Programming Language :: Python :: 3.11
Classifier: Programming Language :: Python :: 3.12
Requires-Python: >=3.10
Requires-Dist: boto3>=1.26.0
Requires-Dist: duckdb>=1.2.0
Requires-Dist: mcp>=1.0.0
Requires-Dist: python-dotenv>=1.0.0
